{
  "$schema": "https://ui.shadcn.com/schema/registry-item.json",
  "name": "checkbox-group",
  "title": "Checkbox Group",
  "description": "Unstyled checkbox group component built on Base UI",
  "dependencies": [
    "@base-ui/react@^1.5.0"
  ],
  "registryDependencies": [
    "@bare-ui/split-variant-props",
    "@bare-ui/tv-config"
  ],
  "files": [
    {
      "path": "registry/bare/ui/checkbox-group/checkbox-group-root.tsx",
      "content": "import { CheckboxGroup as CheckboxGroupPrimitive } from \"@base-ui/react/checkbox-group\";\nimport { createPropSplitter } from \"@/registry/bare/lib/split-variant-props\";\nimport { checkboxGroupStyles } from \"./styles\";\nimport type { VariantProps } from \"@/registry/bare/lib/tv.config\";\n\ntype CheckboxGroupVariantProps = VariantProps<typeof checkboxGroupStyles>;\nconst splitProps = createPropSplitter(checkboxGroupStyles);\n\ninterface CheckboxGroupRootProps extends CheckboxGroupPrimitive.Props, CheckboxGroupVariantProps {\n  className?: string;\n  styles?: ReturnType<typeof checkboxGroupStyles>;\n}\n\nexport function CheckboxGroupRoot(props: CheckboxGroupRootProps) {\n  const [variantProps, { className, styles, ...htmlProps }] = splitProps(props);\n  const s = styles ?? checkboxGroupStyles(variantProps);\n  return <CheckboxGroupPrimitive {...htmlProps} className={s.root({ class: className })} data-slot=\"checkbox-group\" />;\n}\n",
      "type": "registry:ui"
    },
    {
      "path": "registry/bare/ui/checkbox-group/styles.ts",
      "content": "import { tv } from \"@/registry/bare/lib/tv.config\";\n\nexport const checkboxGroupStyles = tv({\n  slots: {\n    root: [\"\"],\n  },\n});\n",
      "type": "registry:ui"
    },
    {
      "path": "registry/bare/ui/checkbox-group/index.parts.ts",
      "content": "export { CheckboxGroupRoot as Root } from \"./checkbox-group-root\";\n",
      "type": "registry:ui"
    },
    {
      "path": "registry/bare/ui/checkbox-group/index.ts",
      "content": "export * as CheckboxGroup from \"./index.parts\";\nexport { checkboxGroupStyles } from \"./styles\";\n",
      "type": "registry:ui"
    }
  ],
  "categories": [
    "form"
  ],
  "type": "registry:ui"
}
